cs/dateutils.py
cs_dateutils-20250724.dist-info/WHEEL
cs_dateutils-20250724.dist-info/METADATA
cs_dateutils-20250724.dist-info/RECORD
